wasp_eureka.py
wasp_eureka/__init__.py
wasp_eureka/__main__.py
wasp_eureka/client.py
wasp_eureka/exc.py
wasp_eureka/log.py
wasp_eureka-1.1.1.dist-info/DESCRIPTION.rst
wasp_eureka-1.1.1.dist-info/METADATA
wasp_eureka-1.1.1.dist-info/RECORD
wasp_eureka-1.1.1.dist-info/WHEEL
wasp_eureka-1.1.1.dist-info/metadata.json
wasp_eureka-1.1.1.dist-info/top_level.txt
