Metadata-Version: 2.0
Name: wasp-eureka
Version: 1.1.1
Summary: Async Eureka client
Home-page: https://github.com/wickedasp/eureka
Author: Matt Rasband
Author-email: matt.rasband@gmail.com
License: Apache-2.0
Download-URL: https://github.com/wickedasp/eureka/archive/v1.1.1.tar.gz
Keywords: microservice,netflixoss,asyncio,springcloud
Platform: UNKNOWN
Classifier: Programming Language :: Python :: 3.5
Classifier: License :: OSI Approved :: Apache Software License
Classifier: Intended Audience :: Developers
Classifier: Development Status :: 4 - Beta
Classifier: Topic :: Software Development
Requires-Dist: aiohttp
Provides-Extra: standalone
Requires-Dist: apscheduler (>=3.3.0); extra == 'standalone'
